strata/__init__.py
strata/__main__.py
strata/cli.py
strata/config.py
strata/logging_config.py
strata/main.py
strata/mcp_client_manager.py
strata/server.py
strata/tools.py
strata/treeshell_functions.py
strata/mcp_proxy/__init__.py
strata/mcp_proxy/auth_provider.py
strata/mcp_proxy/client.py
strata/mcp_proxy/transport/__init__.py
strata/mcp_proxy/transport/base.py
strata/mcp_proxy/transport/http.py
strata/mcp_proxy/transport/stdio.py
strata/utils/__init__.py
strata/utils/bm25_search.py
strata/utils/catalog.py
strata/utils/dict_utils.py
strata/utils/field_search.py
strata/utils/shared_search.py
strata/utils/tool_integration.py
gnosys_strata-1.1.6.dist-info/METADATA
gnosys_strata-1.1.6.dist-info/WHEEL
gnosys_strata-1.1.6.dist-info/entry_points.txt
gnosys_strata-1.1.6.dist-info/RECORD
